kiota_abstractions/__init__.py
kiota_abstractions/_version.py
kiota_abstractions/api_client_builder.py
kiota_abstractions/api_error.py
kiota_abstractions/authentication/__init__.py
kiota_abstractions/authentication/access_token_provider.py
kiota_abstractions/authentication/allowed_hosts_validator.py
kiota_abstractions/authentication/anonymous_authentication_provider.py
kiota_abstractions/authentication/api_key_authentication_provider.py
kiota_abstractions/authentication/authentication_provider.py
kiota_abstractions/authentication/base_bearer_token_authentication_provider.py
kiota_abstractions/base_request_builder.py
kiota_abstractions/base_request_configuration.py
kiota_abstractions/date_utils.py
kiota_abstractions/default_query_parameters.py
kiota_abstractions/get_path_parameters.py
kiota_abstractions/headers_collection.py
kiota_abstractions/method.py
kiota_abstractions/multipart_body.py
kiota_abstractions/native_response_handler.py
kiota_abstractions/py.typed
kiota_abstractions/request_adapter.py
kiota_abstractions/request_information.py
kiota_abstractions/request_option.py
kiota_abstractions/response_handler.py
kiota_abstractions/serialization/__init__.py
kiota_abstractions/serialization/additional_data_holder.py
kiota_abstractions/serialization/composed_type_wrapper.py
kiota_abstractions/serialization/parsable.py
kiota_abstractions/serialization/parsable_factory.py
kiota_abstractions/serialization/parse_node.py
kiota_abstractions/serialization/parse_node_factory.py
kiota_abstractions/serialization/parse_node_factory_registry.py
kiota_abstractions/serialization/parse_node_helper.py
kiota_abstractions/serialization/parse_node_proxy_factory.py
kiota_abstractions/serialization/serialization_writer.py
kiota_abstractions/serialization/serialization_writer_factory.py
kiota_abstractions/serialization/serialization_writer_factory_registry.py
kiota_abstractions/serialization/serialization_writer_proxy_factory.py
kiota_abstractions/store/__init__.py
microsoft_kiota_abstractions-1.9.1.dist-info/LICENSE
microsoft_kiota_abstractions-1.9.1.dist-info/METADATA
microsoft_kiota_abstractions-1.9.1.dist-info/WHEEL
microsoft_kiota_abstractions-1.9.1.dist-info/RECORD
